README.md
gol.py
setup.py
uu_game_of_life.egg-info/PKG-INFO
uu_game_of_life.egg-info/SOURCES.txt
uu_game_of_life.egg-info/dependency_links.txt
uu_game_of_life.egg-info/requires.txt
uu_game_of_life.egg-info/top_level.txt