Metadata-Version: 1.0
Name: uu-game-of-life
Version: 1.0
Summary: Example package of game of life
Home-page: https://github.com/Hakanwie/uu-gol.git
Author: Håkan Wieslander
Author-email: hakan.wieslander@it.uu.se
License: UNKNOWN
Platform: UNKNOWN
